randssl/__init__.py
randssl/randssl.py
randssl-0.0.3.dist-info/LICENSE
randssl-0.0.3.dist-info/METADATA
randssl-0.0.3.dist-info/WHEEL
randssl-0.0.3.dist-info/top_level.txt
randssl-0.0.3.dist-info/RECORD
