Metadata-Version: 2.1
Name: randssl
Version: 0.0.3
Summary: A Python library for generating random SSL.
Author: lanXuage
Author-email: lanxuage@gmail.com
License: MIT
License-File: LICENSE
